Workbook

Sheet Hoja 1
A1: Prioridad | B1: Nombre del Logro | C1: Link Wiki | D1: Categoria | E1: Dificultad | F1: Tipo de Tiempo | G1: Que hacer exactamente | H1: Completado
A2: 01. EMPEZAR HOY | B2: Port Life | C2: =VLOOKUP(B2, runescape_achievements!A:G, 7, FALSE) -> https://runescape.wiki/w/Port_Life | D2: Player Owned Port | E2: Facil | F2: Time-Gated | G2: Habla con el Portmaster en Port Sarim y completa el tutorial. | H2: TRUE
A3: 07. META FINAL | B3: Music Maestro | C3: =VLOOKUP(B3, runescape_achievements!A:G, 7, FALSE) -> https://runescape.wiki/w/Music_Maestro | D3: Activities | E3: Dificil | F3: Exploracion | G3: Desbloquea las 1 | H3: FALSE
A4: 07. META FINAL | B4: Task Master | C4: =VLOOKUP(B4, runescape_achievements!A:G, 7, FALSE) -> https://runescape.wiki/w/Task_Master | D4: Area Tasks | E4: Dificil | F4: Grind Largo | G4: Completa TODOS los logros de área (Easy Medium Hard y Elite) de todas las regiones. | H4: FALSE
A5: 01. EMPEZAR HOY | B5: Top Town Hall | C5: =VLOOKUP(B5, runescape_achievements!A:G, 7, FALSE) -> https://runescape.wiki/w/Top_Town_Hall | D5: Exploration | E5: Facil | F5: Time-Gated | G5: Asigna trabajadores y junta recursos diarios en Anachronia para subir el Town Hall a T3. | H5: TRUE
A6: 06. PVM & COMBATE | B6: Annihilator | C6: =VLOOKUP(B6, runescape_achievements!A:G, 7, FALSE) -> https://runescape.wiki/w/Annihilator | D6: Lore | E6: Dificil | F6: Combate | G6: Ataca a los 4 Nihils a la vez (Sombre Ice Blood Smoke) y mátalos en el mismo combate. | H6: FALSE
A7: 07. META FINAL | B7: I've Got a Little List (of Miniquests) | C7: =VLOOKUP(B7, runescape_achievements!A:G, 7, FALSE) -> https://runescape.wiki/w/I%27ve_Got_a_Little_List_(of_Miniquests) | D7: Lore | E7: Dificil | F7: Misiones | G7: Completa TODAS las miniquests secundarias del diario. | H7: FALSE
A8: 06. PVM & COMBATE | B8: Slayer Master | C8: =VLOOKUP(B8, runescape_achievements!A:G, 7, FALSE) -> https://runescape.wiki/w/Slayer_Master_(achievement) | D8: Skills | E8: Dificil | F8: Combate | G8: Alcanza la ola requerida en la dificultad Platinum de Rush of Blood. | H8: FALSE
A9: 02. REGALADOS | B9: Undead to Rites | C9: =VLOOKUP(B9, runescape_achievements!A:G, 7, FALSE) -> https://runescape.wiki/w/Undead_to_Rites | D9: Area Tasks | E9: Facil | F9: Inmediato | G9: Usa el encantamiento "Ungael Teleport" para aparecer en el sitio del ritual. | H9: TRUE
A10: 07. META FINAL | B10: Master Skiller | C10: =VLOOKUP(B10, runescape_achievements!A:G, 7, FALSE) -> https://runescape.wiki/w/Master_Skiller | D10: Skills | E10: Dificil | F10: Grind Largo | G10: Sube todas las habilidades a sus niveles máximos (120 en aplicables 99 en el resto). | H10: FALSE
A11: 02. REGALADOS | B11: Slide To The Left | C11: =VLOOKUP(B11, runescape_achievements!A:G, 7, FALSE) -> https://runescape.wiki/w/Slide_To_The_Left | D11: Treasure Trails | E11: Facil | F11: Inmediato | G11: Resuelve un puzle de deslizamiento (Slide Box) con Alt1. | H11: TRUE
A12: 03. SKILLING & MID | B12: Bill & Ben's Egg/Salon Joint Venture | C12: =VLOOKUP(B12, runescape_achievements!A:G, 7, FALSE) -> https://runescape.wiki/w/Bill_%26_Ben%27s_Egg/Salon_Joint_Venture | D12: Activities | E12: Facil | F12: Inmediato | G12: Tras la misión Extinction | H12: FALSE
A13: 02. REGALADOS | B13: Untangled | C13: =VLOOKUP(B13, runescape_achievements!A:G, 7, FALSE) -> https://runescape.wiki/w/Untangled | D13: Treasure Trails | E13: Facil | F13: Inmediato | G13: Resuelve un puzle de nudo céltico (Celtic Knot) con Alt1. | H13: TRUE
... A103: 03. SKILLING & MID | B103: Gaps, Traps and Laps | C103: =VLOOKUP(B103, runescape_achievements!A:G, 7, FALSE) -> https://runescape.wiki/w/Gaps,_Traps_and_Laps | D103: _Traps_and_Laps | E103: Skills | F103: Media | G103: Grind Corto | H103: FALSE

Sheet runescape_achievements
A1: Name | B1: Description | C1: Category | D1: Subcategory | E1: Subsubcategory | F1: Release date | G1: Wiki Link
A2: Phite Club | B2: Complete this quest. | C2: Lore | D2: Quests | F2: 5 June 2017 | G2: https://runescape.wiki/w/%27Phite_Club_(achievement)
A3: Phite for Your Right I | B3: Complete a city quest from an inhabitant of Menaphos. | C3: Exploration | D3: Menaphos | F3: 5 June 2017 | G3: https://runescape.wiki/w/%27Phite_for_Your_Right_I
A4: Phite for Your Right II | B4: Complete 10 city quests from an inhabitant of Menaphos. (X/10) | C4: Exploration | D4: Menaphos | F4: 5 June 2017 | G4: https://runescape.wiki/w/%27Phite_for_Your_Right_II
A5: Phite for Your Right III | B5: Complete 50 city quests from an inhabitant of Menaphos. (X/50) | C5: Exploration | D5: Menaphos | F5: 5 June 2017 | G5: https://runescape.wiki/w/%27Phite_for_Your_Right_III
A6: Phite for Your Right IV | B6: Complete 100 city quests from an inhabitant of Menaphos. (X/100) | C6: Exploration | D6: Menaphos | F6: 5 June 2017 | G6: https://runescape.wiki/w/%27Phite_for_Your_Right_IV
A7: Phite for Your Right V | B7: Complete 200 city quests from an inhabitant of Menaphos. (X/200) | C7: Exploration | D7: Menaphos | F7: 5 June 2017 | G7: https://runescape.wiki/w/%27Phite_for_Your_Right_V
A8: (Do Not) Abandon Hope I | B8: Complete an abandoned 1 floor within 12 minutes. Requirements: 1:1 party size:difficulty, large dungeon, high complexity, 100% explored | C8: Skills | D8: Dungeoneering | E8: Speedrunning | F8: 46160 | G8: https://runescape.wiki/w/(Do_Not)_Abandon_Hope_I
A9: (Do Not) Abandon Hope II | B9: Complete an abandoned 1 floor within 8 minutes. Requirements: 1:1 party size:difficulty, large dungeon, high complexity, 100% explored | C9: Skills | D9: Dungeoneering | E9: Speedrunning | F9: 46160 | G9: https://runescape.wiki/w/(Do_Not)_Abandon_Hope_II
A10: (Do Not) Abandon Hope III | B10: Complete an abandoned 1 floor within 6 minutes 15 seconds. Requirements: 1:1 party size:difficulty, large dungeon, high complexity, 100% explored | C10: Skills | D10: Dungeoneering | E10: Speedrunning | F10: 46160 | G10: https://runescape.wiki/w/(Do_Not)_Abandon_Hope_III
A11: (Living on a) Prayer 92 | B11: Reach level 92 in the Prayer skill. | C11: Skills | D11: Prayer | F11: 18 April 2017 | G11: https://runescape.wiki/w/(Living_on_a)_Prayer_92
A12: ...You'd Best Come A-cookin' | B12: Cook a rocktail on a range in the Falador area. | C12: Area Tasks | D12: Elite Falador | F12: 7 September 2010 | G12: https://runescape.wiki/w/...You%27d_Best_Come_A-cookin%27
A13: 61 Shades of Red | B13: Obtained a collection of unique drops from Slayer monsters from and around Daemonheim. | C13: Feats | D13: Slayer Logs | F13: 23 September 2019 | G13: https://runescape.wiki/w/61_Shades_of_Red
A14: 99 With a Flake | B14: Unfurl a flag in the Max Guild garden or jump for joy if you have already unfurled them all. | C14: Area Tasks | D14: Elite Tirannwn | F14: 15 December 2014 | G14: https://runescape.wiki/w/99_With_a_Flake
A15: 300 | B15: Complete Three's Company with 100%. | C15: Area Tasks | D15: Medium Daemonheim | F15: 10 September 2013 | G15: https://runescape.wiki/w/300
A16: 1001 Kharidian Spikes | B16: Harvest spines from a cactus you grew yourself in Al Kharid. | C16: Area Tasks | D16: Hard Desert | F16: 21 January 2013 | G16: https://runescape.wiki/w/1001_Kharidian_Spikes
A17: A Barrel of Staffs | B17: Purchase a God staff from the Chamber guardian in the Mage Arena. | C17: Area Tasks | D17: Medium Wilderness | F17: 8 August 2016 | G17: https://runescape.wiki/w/A_Barrel_of_Staffs
A18: A Bit TOO Familiar | B18: Play as the following familiars in Familiarisation. | C18: Activities | D18: Distractions & Diversions | F18: 5 November 2018 | G18: https://runescape.wiki/w/A_Bit_TOO_Familiar
A19: A Blight of Bloom and Hatchets | B19: Work with Ramarno (in Camdozaal) to obtain a hatchet of bloom and blight. (X/9) | C19: Skills | D19: Woodcutting | F19: 9 December 2024 | G19: https://runescape.wiki/w/A_Blight_of_Bloom_and_Hatchets
A20: A Body in the Sewers | B20: Smith a mithril platebody on the anvil in the jailhouse sewers. | C20: Area Tasks | D20: Hard Lumbridge | F20: 7 September 2010 | G20: https://runescape.wiki/w/A_Body_in_the_Sewers
A21: A Bolt from the Bane | B21: Smith and fletch 10 bane bolts at once within Varrock. | C21: Area Tasks | D21: Elite Varrock | F21: 7 September 2010 | G21: https://runescape.wiki/w/A_Bolt_from_the_Bane
A22: A Bridge Not Far | B22: Cross the River Lum using a crossbow. | C22: Area Tasks | D22: Medium Desert | F22: 21 January 2013 | G22: https://runescape.wiki/w/A_Bridge_Not_Far
A23: A Brief History of Telescopes | B23: Discover the pieces of a famous quote from Stephen Hawking. (X/4) | C23: Feats | D23: Events | F23: 19 March 2018 | G23: https://runescape.wiki/w/A_Brief_History_of_Telescopes
A24: A bug in the system | B24: Find and read the scruffy note in the Scabarite Cavern. | C24: Lore | D24: Books | F24: 25 November 2024 | G24: https://runescape.wiki/w/A_bug_in_the_system
A25: A Cat is For Life... | B25: Talk to a civilian in West Ardougne about selling a cat. | C25: Area Tasks | D25: Easy Ardougne | F25: 10 October 2009 | G25: https://runescape.wiki/w/A_Cat_is_For_Life...
A26: A Change of Pace | B26: Unlock the ability to change your spellbook using War's Grimoire at War's Retreat. | C26: Combat | D26: PvM Hub: War's Retreat | F26: 17 February 2025 | G26: https://runescape.wiki/w/A_Change_of_Pace
A27: A Charm Saved is a Charm Earned | B27: Charge or combine a spirit gem. | C27: Skills | D27: Summoning | F27: 5 November 2018 | G27: https://runescape.wiki/w/A_Charm_Saved_is_a_Charm_Earned
... A47: A Grave Consideration | B47: Look through Father Aereck's selection of gravestones. | C47: Area Tasks | D47: Beginner Lumbridge | F47: 14 July 2008 | G47: https://runescape.wiki/w/A_Grave_Consideration
A48: A Hatching Pair | B48: After Extinction quest, ask Prehistoric Potterington at the Anachronia dinosaur farm about zygomites. | C48: Activities | D48: Accidental' Skilling Station | F48: 44684 | G48: https://runescape.wiki/w/A_Hatching_Pair
A49: A Hidden Gem I | B49: Shatter a crystal geode. (X/1) | C49: Skills | D49: Woodcutting | F49: 5 November 2018 | G49: https://runescape.wiki/w/A_Hidden_Gem_I
A50: A Hidden Gem II | B50: Shatter 5 crystal geodes. (X/5) | C50: Skills | D50: Woodcutting | F50: 5 November 2018 | G50: https://runescape.wiki/w/A_Hidden_Gem_II
A51: A Hidden Gem III | B51: Shatter 10 crystal geodes. (X/10) | C51: Skills | D51: Woodcutting | F51: 5 November 2018 | G51: https://runescape.wiki/w/A_Hidden_Gem_III
A52: A Hidden Gem IV | B52: Shatter 25 crystal geodes. (X/25) | C52: Skills | D52: Woodcutting | F52: 5 November 2018 | G52: https://runescape.wiki/w/A_Hidden_Gem_IV
A53: A Knight in the Darkness | B53: Ascend the Dark Wizards' Tower while wearing full proselyte armour. | C53: Area Tasks | D53: Hard Falador | F53: 9 December 2008 | G53: https://runescape.wiki/w/A_Knight_in_the_Darkness
A54: A Lick of Paint | B54: Select a colour for a new kitten. | C54: Area Tasks | D54: Medium Varrock | F54: 10 September 2007 | G54: https://runescape.wiki/w/A_Lick_of_Paint
A55: A Life of Death and Pickaxes | B55: Work with Ramarno (in Camdozaal) to obtain a pickaxe of life and death. (X/9) | C55: Skills | D55: Mining | F55: 12 August 2024 | G55: https://runescape.wiki/w/A_Life_of_Death_and_Pickaxes
A56: A Little Overdressed | B56: Wear a full diving outfit to go diving in Everlight. | C56: Skills | D56: Archaeology | E56: Saradominist | F56: 30 March 2020 | G56: https://runescape.wiki/w/A_Little_Overdressed
A57: A Meal Fit For a Duke | B57: Cook a lobster on the range in Lumbridge Castle's kitchen. | C57: Area Tasks | D57: Medium Lumbridge | F57: 14 July 2008 | G57: https://runescape.wiki/w/A_Meal_Fit_For_a_Duke
A58: A Mini Shipment | B58: Loot the trunk in the Temple of Aminishi. | C58: Combat | D58: Shadow Reef | F58: 25 February 2019 | G58: https://runescape.wiki/w/A_Mini_Shipment
A59: A Natural Thief | B59: Attempt to steal a nature rune from a chest in a house to the east of Ardougne market. | C59: Area Tasks | D59: Medium Ardougne | F59: 10 October 2009 | G59: https://runescape.wiki/w/A_Natural_Thief
A60: A New Age | B60: Solve this mystery. | C60: Skills | D60: Archaeology | E60: Dragonkin | F60: 10 June 2024 | G60: https://runescape.wiki/w/A_New_Age
A61: A New Direction | B61: Reunite Irwinsson with his lost compass. | C61: Exploration | D61: Anachronia | F61: 8 July 2019 | G61: https://runescape.wiki/w/A_New_Direction
A62: A New Discovery | B62: After upgrading the grove at Fort Forinthry to Tier 3, return to Oak to learn about his new discovery. | C62: Exploration | D62: Fort Forinthry | F62: 19 June 2023 | G62: https://runescape.wiki/w/A_New_Discovery
A63: A New Form | B63: Solve this mystery. | C63: Skills | D63: Archaeology | E63: Dragonkin | F63: 10 June 2024 | G63: https://runescape.wiki/w/A_New_Form
A64: A New Home | B64: Solve this mystery. | C64: Skills | D64: Archaeology | E64: Dragonkin | F64: 10 June 2024 | G64: https://runescape.wiki/w/A_New_Home
A65: A Palm For Each Finger | B65: Collect 5 palm leaves. | C65: Area Tasks | D65: Hard Karamja | F65: 39210 | G65: https://runescape.wiki/w/A_Palm_For_Each_Finger
A66: A Periodic Table | B66: Get mahogany from your Etceterian subjects. | C66: Area Tasks | D66: Hard Fremennik | F66: 9 December 2008 | G66: https://runescape.wiki/w/A_Periodic_Table
A67: A Pizza the Loot | B67: Create an anchovy pizza from scratch in the Bandit Camp and give it to Fat Tony. (X/5) | C67: Area Tasks | D67: Medium Wilderness | F67: 8 August 2016 | G67: https://runescape.wiki/w/A_Pizza_the_Loot
A68: A Place For My Heads | B68: Mount all three of the Raptor's slayer trophies. | C68: Skills | D68: Slayer | F68: 11 April 2023 | G68: https://runescape.wiki/w/A_Place_For_My_Heads
A69: A Prayer for the Dying | B69: Talk to Selene to learn a Necromancy prayer. | C69: Area Tasks | D69: Easy Underworld | F69: 7 August 2023 | G69: https://runescape.wiki/w/A_Prayer_for_the_Dying
A70: A Prayer Opportunity | B70: Build a prayer altar in the starting room and fill up your prayer points from it. | C70: Area Tasks | D70: Hard Daemonheim | F70: 10 September 2013 | G70: https://runescape.wiki/w/A_Prayer_Opportunity
A71: A Purr-fect Toss | B71: Throw an Explosive Scarab Akh at Amascut, the Devourer. | C71: Combat | D71: Amascut | F71: 29 September 2025 | G71: https://runescape.wiki/w/A_Purr-fect_Toss
A72: A Quest for Understanding | B72: Defeat Astellarn while at least two pulsars are still active. | C72: Combat | D72: Dragonkin Laboratory | E72: Astellarn | F72: 13 August 2018 | G72: https://runescape.wiki/w/A_Quest_for_Understanding
A73: A Reptile's Dysfunction | B73: Upgrade Zorgoth's ring by completing rituals at the Ungael ritual site. | C73: Skills | D73: Necromancy | F73: 22 April 2024 | G73: https://runescape.wiki/w/A_Reptile%27s_Dysfunction
A74: A Road Less Travelled | B74: Pass the guards guarding the Wilderness entrance. | C74: Area Tasks | D74: Easy Daemonheim | F74: 10 September 2013 | G74: https://runescape.wiki/w/A_Road_Less_Travelled
A75: A Seer-ing Light | B75: Pray at the Seers' Village altar. | C75: Area Tasks | D75: Easy Seers' Village | F75: 20 January 2009 | G75: https://runescape.wiki/w/A_Seer-ing_Light
A76: A Shadow over Ashdale | B76: Complete this quest. | C76: Lore | D76: Quests | F76: 18 April 2017 | G76: https://runescape.wiki/w/A_Shadow_over_Ashdale_(achievement)
A77: A Slippery Slope I | B77: Defeat the Arch-Glacor. (X/5) | C77: Combat | D77: Arch-Glacor | F77: 31 August 2021 | G77: https://runescape.wiki/w/A_Slippery_Slope_I
A78: A Slippery Slope II | B78: Defeat the Arch-Glacor. (X/10) | C78: Combat | D78: Arch-Glacor | F78: 31 August 2021 | G78: https://runescape.wiki/w/A_Slippery_Slope_II
A79: A Slippery Slope III | B79: Defeat the Arch-Glacor. (X/25) | C79: Combat | D79: Arch-Glacor | F79: 31 August 2021 | G79: https://runescape.wiki/w/A_Slippery_Slope_III
A80: A Slippery Slope IV | B80: Defeat the Arch-Glacor. (X/50) | C80: Combat | D80: Arch-Glacor | F80: 31 August 2021 | G80: https://runescape.wiki/w/A_Slippery_Slope_IV
A81: A Slippery Slope V | B81: Defeat the Arch-Glacor. (X/75) | C81: Combat | D81: Arch-Glacor | F81: 31 August 2021 | G81: https://runescape.wiki/w/A_Slippery_Slope_V
A82: A Slippery Slope VI | B82: Defeat the Arch-Glacor. (X/100) | C82: Combat | D82: Arch-Glacor | F82: 31 August 2021 | G82: https://runescape.wiki/w/A_Slippery_Slope_VI
A83: A Sliver of Silver Helps the Sanguine Go Down | B83: Learn how to smith more durable havensilver. | C83: Lore | D83: Post-Quest | F83: 30 March 2026 | G83: https://runescape.wiki/w/A_Sliver_of_Silver_Helps_the_Sanguine_Go_Down
A84: A Song of Earth and Pickaxes | B84: Work with the blast furnace foreman (in Keldagrim) to obtain a pickaxe of earth and song. | C84: Skills | D84: Mining | F84: 7 January 2019 | G84: https://runescape.wiki/w/A_Song_of_Earth_and_Pickaxes
... A94: A String and a Flare | B94: Cast the String Jewellery spell while standing at the furnace in Falador. | C94: Area Tasks | D94: Elite Falador | F94: 7 September 2010 | G94: https://runescape.wiki/w/A_String_and_a_Flare
A95: A Study in Aether | B95: Solve this mystery. | C95: Skills | D95: Archaeology | E95: Armadylean | F95: 30 March 2020 | G95: https://runescape.wiki/w/A_Study_in_Aether
A96: A Swift Two Fifty | B96: Collect 250 or more tears from a single entry in Tears of Guthix. | C96: Activities | D96: Distractions & Diversions | F96: 5 November 2018 | G96: https://runescape.wiki/w/A_Swift_Two_Fifty
A97: A Tail of Two Cats | B97: Complete this quest. | C97: Lore | D97: Quests | F97: 18 April 2017 | G97: https://runescape.wiki/w/A_Tail_of_Two_Cats_(achievement)
A98: A Taste of the Exotic | B98: Pick a papaya or coconut from the fruit tree patch near Tree Gnome Village. | C98: Area Tasks | D98: Hard Ardougne | F98: 10 October 2009 | G98: https://runescape.wiki/w/A_Taste_of_the_Exotic
A99: A Thief Beyond Belief | B99: Steal from each of the listed types of merchant stalls. | C99: Skills | D99: Thieving | F99: 5 November 2018 | G99: https://runescape.wiki/w/A_Thief_Beyond_Belief
A100: A Ton of Earth | B100: Craft 100 earth runes simultaneously without aid from an explorer's ring, pouches or familiars. | C100: Area Tasks | D100: Elite Varrock | F100: 7 September 2010 | G100: https://runescape.wiki/w/A_Ton_of_Earth
A101: A View to Die For | B101: Find the amazing viewpoint overlooking the City of Um that will give you hours of enjoyment. | C101: Area Tasks | D101: Easy Underworld | F101: 7 August 2023 | G101: https://runescape.wiki/w/A_View_to_Die_For
A102: A Visit to Charlie | B102: Enter the unicorn pen in Ardougne Zoo using the fairy rings. | C102: Area Tasks | D102: Medium Ardougne | F102: 10 October 2009 | G102: https://runescape.wiki/w/A_Visit_to_Charlie
A103: A Void Dance | B103: Complete this quest. | C103: Lore | D103: Quests | F103: 18 April 2017 | G103: https://runescape.wiki/w/A_Void_Dance_(achievement)
A104: A Wizard Did It | B104: Talk to the wizard Avalani within a clan citadel. | C104: Activities | D104: Clans | F104: 18 April 2017 | G104: https://runescape.wiki/w/A_Wizard_Did_It
A105: A, B, Cithara | B105: Play the Holy Cithara while standing in the Citharede Abbey. | C105: Area Tasks | D105: Elite Desert | F105: 21 January 2013 | G105: https://runescape.wiki/w/A,_B,_Cithara
A106: A-Voiding Conflict | B106: Win a Pest Control game after repairing all barricades to full. | C106: Activities | D106: Minigames | F106: 18 April 2017 | G106: https://runescape.wiki/w/A-Voiding_Conflict
A107: Abandoned At A Pace I | B107: Complete an abandoned 1 floor within 6 minutes. Requirements: 5:5 party size:difficulty, large dungeon, high complexity, 100% explored | C107: Skills | D107: Dungeoneering | E107: Speedrunning | F107: 46160 | G107: https://runescape.wiki/w/Abandoned_At_A_Pace_I
A108: Abandoned At A Pace II | B108: Complete an abandoned 1 floor within 4 minutes. Requirements: 5:5 party size:difficulty, large dungeon, high complexity, 100% explored | C108: Skills | D108: Dungeoneering | E108: Speedrunning | F108: 46160 | G108: https://runescape.wiki/w/Abandoned_At_A_Pace_II
A109: Abandoned At A Pace III | B109: Complete an abandoned 1 floor within 2 minutes 30 seconds. Requirements: 5:5 party size:difficulty, large dungeon, high complexity, 100% explored | C109: Skills | D109: Dungeoneering | E109: Speedrunning | F109: 46160 | G109: https://runescape.wiki/w/Abandoned_At_A_Pace_III
A110: Abbinah Resting Here For a While | B110: Find every ancient aviansie spirit at Stormguard. | C110: Skills | D110: Archaeology | E110: Armadylean | F110: 30 March 2020 | G110: https://runescape.wiki/w/Abbinah_Resting_Here_For_a_While
A111: Absolute Planker | B111: Upgrade your plank box to hold 100 of each plank. | C111: Skills | D111: Construction | E111: Contracts | F111: 16 November 2020 | G111: https://runescape.wiki/w/Absolute_Planker
A112: Abyssal Shortcut | B112: Unlock the asylum gate and complete the shortcut to the abyssal portal. | C112: Skills | D112: Slayer | F112: 28 February 2022 | G112: https://runescape.wiki/w/Abyssal_Shortcut
A113: Abyssal Valet | B113: Have an abyssal titan familiar hold essence for you while runecrafting at Ourania Altar. | C113: Area Tasks | D113: Elite Ardougne | F113: 10 October 2009 | G113: https://runescape.wiki/w/Abyssal_Valet
A114: Accelerated Abandoned I | B114: Complete an abandoned 2 floor within 12 minutes. Requirements: 1:1 party size:difficulty, large dungeon, high complexity, 100% explored | C114: Skills | D114: Dungeoneering | E114: Speedrunning | F114: 46160 | G114: https://runescape.wiki/w/Accelerated_Abandoned_I
A115: Accelerated Abandoned II | B115: Complete an abandoned 2 floor within 8 minutes. Requirements: 1:1 party size:difficulty, large dungeon, high complexity, 100% explored | C115: Skills | D115: Dungeoneering | E115: Speedrunning | F115: 46160 | G115: https://runescape.wiki/w/Accelerated_Abandoned_II
A116: Accelerated Abandoned III | B116: Complete an abandoned 2 floor within 6 minutes 15 seconds. Requirements: 1:1 party size:difficulty, large dungeon, high complexity, 100% explored | C116: Skills | D116: Dungeoneering | E116: Speedrunning | F116: 46160 | G116: https://runescape.wiki/w/Accelerated_Abandoned_III
A117: Ace of Dungeons | B117: Talk to the gorajo hoardstalker while under the influence of a perfect dungeoneering juju potion. | C117: Area Tasks | D117: Elite Tirannwn | F117: 15 December 2014 | G117: https://runescape.wiki/w/Ace_of_Dungeons
A118: Acid-washed | B118: Defeat Araxxor and Araxxi while at most 10% of the total acid remains in the pool after taking the Acid path during phase 2. | C118: Combat | D118: Araxxi | F118: 17 February 2025 | G118: https://runescape.wiki/w/Acid-washed
A119: Ad-Myre The Goods | B119: View the stock in Razmire Builders' Merchants shop. | C119: Area Tasks | D119: Medium Morytania | F119: 27 March 2012 | G119: https://runescape.wiki/w/Ad-Myre_The_Goods
A120: Advanced Soul Forgery | B120: Upgrade a piece of Death Skull or Deathwarden equipment to tier 50. | C120: Area Tasks | D120: Medium Underworld | F120: 7 August 2023 | G120: https://runescape.wiki/w/Advanced_Soul_Forgery
A121: Advanced Sweeping | B121: Fully enchant your broomstick after the 'Swept Away' quest. | C121: Lore | D121: Post-Quest | F121: 18 April 2017 | G121: https://runescape.wiki/w/Advanced_Sweeping
A122: Aereck's Old Bones | B122: Claim ancient bones from Father Aereck after 'The Restless Ghost'. | C122: Lore | D122: Post-Quest | F122: 18 April 2017 | G122: https://runescape.wiki/w/Aereck%27s_Old_Bones
A123: Aerial Pursuit | B123: Defeat Barrows: Rise of the Six without anyone being hit by Verac's 'Deathcopter' attack. | C123: Combat | D123: Barrows: Rise of the Six | F123: 17 February 2025 | G123: https://runescape.wiki/w/Aerial_Pursuit
A124: After the Close | B124: Unlock the Closure's robes cosmetic override outfit after 'Once Upon a Time in Gielinor'. | C124: Lore | D124: Post-Quest | F124: 6 December 2021 | G124: https://runescape.wiki/w/After_the_Close
A125: After the Flood | B125: Find and read Elidinis' memoir. | C125: Lore | D125: Books | F125: 16 September 2024 | G125: https://runescape.wiki/w/After_the_Flood_(achievement)
A126: Aftermath | B126: Complete this quest. | C126: Lore | D126: Quests | F126: 4 July 2022 | G126: https://runescape.wiki/w/Aftermath_(achievement)
A127: Aged Journal | B127: Find and read the Aged Journal in Daemonheim. | C127: Lore | D127: Books | F127: 24 March 2025 | G127: https://runescape.wiki/w/Aged_Journal_(achievement)
A128: Agile Abandoned I | B128: Complete an abandoned 2 floor within 6 minutes. Requirements: 5:5 party size:difficulty, large dungeon, high complexity, 100% explored | C128: Skills | D128: Dungeoneering | E128: Speedrunning | F128: 46160 | G128: https://runescape.wiki/w/Agile_Abandoned_I
...
